xdggs/__init__.py
xdggs/accessor.py
xdggs/ellipsoid.py
xdggs/grid.py
xdggs/h3.py
xdggs/healpix.py
xdggs/index.py
xdggs/itertools.py
xdggs/tutorial.py
xdggs/utils.py
xdggs/plotting/__init__.py
xdggs/plotting/arrow.py
xdggs/plotting/colorbar.js
xdggs/plotting/colorbar.py
xdggs/plotting/colorize.py
xdggs/plotting/map.js
xdggs/plotting/map.py
xdggs/plotting/variables.py
xdggs/tests/__init__.py
xdggs/tests/matchers.py
xdggs/tests/strategies.py
xdggs/tests/test_accessor.py
xdggs/tests/test_h3.py
xdggs/tests/test_healpix.py
xdggs/tests/test_index.py
xdggs/tests/test_matchers.py
xdggs/tests/test_plotting.py
xdggs/tests/test_tutorial.py
xdggs/tests/test_utils.py
xdggs-0.5.0.dist-info/METADATA
xdggs-0.5.0.dist-info/WHEEL
xdggs-0.5.0.dist-info/licenses/LICENSE
xdggs-0.5.0.dist-info/RECORD
