Metadata-Version: 2.4
Name: xdggs
Version: 0.5.0
Summary: Xarray extension for DGGS
Project-URL: Documentation, https://xdggs.readthedocs.io
Project-URL: Repository, https://github.com/xarray-contrib/xdggs
Author: Benoît Bovy, Justus Magin
Maintainer: xdggs contributors
License: Apache-2.0
License-File: LICENSE
Keywords: DGGS,GIS,xarray
Classifier: Intended Audience :: Science/Research
Classifier: License :: OSI Approved :: Apache Software License
Classifier: Operating System :: OS Independent
Classifier: Programming Language :: Python :: 3
Classifier: Programming Language :: Python :: 3.11
Classifier: Programming Language :: Python :: 3.12
Classifier: Programming Language :: Python :: 3.13
Classifier: Topic :: Scientific/Engineering :: GIS
Requires-Python: >=3.11
Requires-Dist: arro3-core>=0.4.0
Requires-Dist: cdshealpix
Requires-Dist: h3ronpy
Requires-Dist: healpix-geo>=0.0.6
Requires-Dist: lonboard>=0.9.3
Requires-Dist: matplotlib
Requires-Dist: numpy>=2.0
Requires-Dist: pooch
Requires-Dist: pyproj>=3.3
Requires-Dist: xarray
